setup.py
micropython_oled.egg-info/PKG-INFO
micropython_oled.egg-info/SOURCES.txt
micropython_oled.egg-info/dependency_links.txt
micropython_oled.egg-info/top_level.txt
oled/__init__.py
oled/gfx.py
oled/lazy.py
oled/ssd1306.py
oled/write.py
oled/examples/example0.py
oled/examples/example1.py
oled/examples/example2.py
oled/examples/example3.py
oled/examples/example4.py
oled/fonts/__init__.py
oled/fonts/bookerly_12.py
oled/fonts/bookerly_15.py
oled/fonts/bookerly_20.py
oled/fonts/gen.py
oled/fonts/press_start_2p_12.py
oled/fonts/press_start_2p_15.py
oled/fonts/press_start_2p_20.py
oled/fonts/ubuntu_12.py
oled/fonts/ubuntu_15.py
oled/fonts/ubuntu_20.py
oled/fonts/ubuntu_condensed_12.py
oled/fonts/ubuntu_condensed_15.py
oled/fonts/ubuntu_condensed_20.py
oled/fonts/ubuntu_mono_12.py
oled/fonts/ubuntu_mono_15.py
oled/fonts/ubuntu_mono_20.py