Metadata-Version: 1.2
Name: micropython-oled
Version: 1.13
Summary: Micropython scripts for use OLED displays.
Home-page: http://yeisoncardona.com/
Author: Yeison Cardona
Author-email: yeisoneng@gmail.com
Maintainer: Yeison Cardona
Maintainer-email: yeisoneng@gmail.com
License: GNU GPL
Download-URL: https://bitbucket.org/espressoide/micropython-oled/downloads/
Platform: UNKNOWN
